ezpgz/__init__.py
ezpgz/dataCache.py
ezpgz/ezActor.py
ezpgz/ezGo.py
ezpgz/ezInput.py
ezpgz-0.0.4.dist-info/METADATA
ezpgz-0.0.4.dist-info/WHEEL
ezpgz-0.0.4.dist-info/licenses/LICENSE.md
ezpgz-0.0.4.dist-info/RECORD
