Metadata-Version: 2.1
Name: ezpgz
Version: 0.0.4
Summary: Example
Project-URL: Homepage, https://github.com/Necrownyx/pgez
Project-URL: Bug Tracker, https://github.com/Necrownyx/pgez/issues
Author-email: Necrownyx <Necrownyx@outlook.com>
License-File: LICENSE.md
Classifier: License :: OSI Approved :: MIT License
Classifier: Operating System :: OS Independent
Classifier: Programming Language :: Python :: 3
Requires-Python: >=3.7
Requires-Dist: pgzero>=1.2
